photoalbum/__init__.py
photoalbum/__main__.py
photoalbum/dicionarioDEmensagens.py
photoalbum/toolsphotoalbum.py
leopaolucci_photoalbum-0.0.1.dist-info/LICENSE
leopaolucci_photoalbum-0.0.1.dist-info/METADATA
leopaolucci_photoalbum-0.0.1.dist-info/WHEEL
leopaolucci_photoalbum-0.0.1.dist-info/entry_points.txt
leopaolucci_photoalbum-0.0.1.dist-info/top_level.txt
leopaolucci_photoalbum-0.0.1.dist-info/RECORD
