Metadata-Version: 2.1
Name: leopaolucci-photoalbum
Version: 0.0.1
Summary: Assembly a photo album with your pictures
Author-email: "Leopoldo A. Paolucci" <leobia2009@yahoo.com.br>
License: MIT License        
Classifier: License :: OSI Approved :: MIT License
Classifier: Programming Language :: Python
Classifier: Programming Language :: Python :: 3
Requires-Python: >=3.8
License-File: LICENSE
Requires-Dist: matplotlib (==3.6.1)
Requires-Dist: PyPDF2 (==2.11.1)
Requires-Dist: setuptools (==65.5.0)
Requires-Dist: tomli ; python_version < "3.11"
Provides-Extra: build
Requires-Dist: build ; extra == 'build'
Requires-Dist: twine ; extra == 'build'
Provides-Extra: dev
Requires-Dist: pip-tools ; extra == 'dev'
Requires-Dist: pytest ; extra == 'dev'
